{
  "suggest.echodocSupport": true,
  "suggest.maxCompleteItemCount": 20,
  "coc.preferences.formatOnSaveFiletypes": [
    "javascript",
    "typescript",
    "typescriptreact",
    "json",
    "javascriptreact",
    "typescript.tsx",
    "svelte",
    "go",
    "rust"
  ],
  "eslint.filetypes": [
    "javascript",
    "typescript",
    "typescriptreact",
    "javascriptreact",
    "typescript.tsx"
  ],
  "diagnostic.errorSign": "•",
  "diagnostic.warningSign": "•",
  "diagnostic.infoSign": "•",
  "diagnostic.messageTarget": "float",
  "diagnostic.enableMessage": "jump",
  "diagnostic.refreshOnInsertMode": false,
  "diagnostic.checkCurrentLine": true,
  "diagnostic.virtualText": true,
  "html.autoClosingTags": true,
  "javascript.format.enabled": false,
  "typescript.format.enabled": false,
  "svelte.plugin.svelte.format.enable": false
}
